unilvq/__init__.py
unilvq/common/__init__.py
unilvq/common/data_handler.py
unilvq/common/data_scaler.py
unilvq/common/early_stopper.py
unilvq/common/scorer.py
unilvq/common/verifier.py
unilvq/core/__init__.py
unilvq/core/base_model.py
unilvq/core/classic_lvq.py
unilvq/core/glvq.py
unilvq/core/grlvq.py
unilvq/core/lgmlvq.py
unilvq-0.2.0.dist-info/licenses/LICENSE
unilvq-0.2.0.dist-info/METADATA
unilvq-0.2.0.dist-info/WHEEL
unilvq-0.2.0.dist-info/top_level.txt
unilvq-0.2.0.dist-info/RECORD
