Metadata-Version: 2.4
Name: unilvq
Version: 0.2.0
Summary: UniLVQ: A Unified Learning Vector Quantization Framework for Supervised Learning Tasks
Home-page: https://github.com/thieu1995/UniLVQ
Author: Thieu
Author-email: nguyenthieu2102@gmail.com
License: GPLv3
Project-URL: Documentation, https://unilvq.readthedocs.io/
Project-URL: Source Code, https://github.com/thieu1995/UniLVQ
Project-URL: Bug Tracker, https://github.com/thieu1995/UniLVQ/issues
Project-URL: Change Log, https://github.com/thieu1995/UniLVQ/blob/main/ChangeLog.md
Project-URL: Forum, https://t.me/+fRVCJGuGJg1mNDg1
Keywords: Learning Vector Quantization,LVQ,Prototype-based Learning,LVQ1,LVQ2.1,LVQ3,GLVQ,GRLVQ,RSLVQ,Distance Learning,Prototype Optimization,Supervised Learning,Classification,Regression,Multi-class Classification,Function Approximation,Regression with Prototypes,PyTorch,Scikit-learn,BaseEstimator,Gradient Descent Optimization,Model Wrapping,Open-source Machine Learning,Model Interpretability,Prototype Visualization,Hybrid Learning,Lightweight Models,Low-Data Regimes,Benchmarking,machine learn
Classifier: Development Status :: 5 - Production/Stable
Classifier: Intended Audience :: Developers
Classifier: Intended Audience :: Education
Classifier: Intended Audience :: Information Technology
Classifier: Intended Audience :: Science/Research
Classifier: License :: OSI Approved :: GNU General Public License v3 (GPLv3)
Classifier: Natural Language :: English
Classifier: Programming Language :: Python :: 3.8
Classifier: Programming Language :: Python :: 3.9
Classifier: Programming Language :: Python :: 3.10
Classifier: Programming Language :: Python :: 3.11
Classifier: Programming Language :: Python :: 3.12
Classifier: Programming Language :: Python :: 3.13
Classifier: Topic :: System :: Benchmark
Classifier: Topic :: Scientific/Engineering
Classifier: Topic :: Scientific/Engineering :: Mathematics
Classifier: Topic :: Scientific/Engineering :: Artificial Intelligence
Classifier: Topic :: Scientific/Engineering :: Information Analysis
Classifier: Topic :: Scientific/Engineering :: Visualization
Classifier: Topic :: Scientific/Engineering :: Bio-Informatics
Classifier: Topic :: Software Development :: Build Tools
Classifier: Topic :: Software Development :: Libraries
Classifier: Topic :: Software Development :: Libraries :: Python Modules
Classifier: Topic :: Utilities
Requires-Python: >=3.8
License-File: LICENSE
Requires-Dist: numpy<=1.26.0,>=1.17.1
Requires-Dist: scipy>=1.7.1
Requires-Dist: scikit-learn>=1.2.1
Requires-Dist: pandas<2.2,>=1.3.5
Requires-Dist: permetrics>=2.0.0
Requires-Dist: torch>=2.0.0
Provides-Extra: dev
Requires-Dist: pytest==7.1.2; extra == "dev"
Requires-Dist: pytest-cov==4.0.0; extra == "dev"
Requires-Dist: flake8>=4.0.1; extra == "dev"
Dynamic: author
Dynamic: author-email
Dynamic: classifier
Dynamic: description
Dynamic: description-content-type
Dynamic: home-page
Dynamic: keywords
Dynamic: license
Dynamic: license-file
Dynamic: project-url
Dynamic: provides-extra
Dynamic: requires-dist
Dynamic: requires-python
Dynamic: summary
